hina/__init__.py
hina/flush_thread.py
hina/sdk.py
HinaCloudSDK-3.9.1.dist-info/LICENSE
HinaCloudSDK-3.9.1.dist-info/METADATA
HinaCloudSDK-3.9.1.dist-info/WHEEL
HinaCloudSDK-3.9.1.dist-info/top_level.txt
HinaCloudSDK-3.9.1.dist-info/RECORD
