Metadata-Version: 2.1
Name: HinaCloudSDK
Version: 3.9.1
Summary: This is the official Python SDK for Hina Analytics.
Home-page: https://github.com/hinadt/hina-cloud-python-sdk.git
Author: hina
Author-email: admin@hinadt.com
License-File: LICENSE
